bpm_tools/__init__.py
bpm_tools/utilities.py
bpm_tools/aws/__init__.py
bpm_tools/aws/dynamodb.py
bpm_tools/aws/glue.py
bpm_tools/aws/s3.py
bpm_tools/misc/__init__.py
bpm_tools/misc/functions.py
bpm_tools/objects/EventUserMap.py
bpm_tools/objects/__init__.py
bpm_tools/pipelines/__init__.py
bpm_tools/pipelines/firehose.py
bpm_tools/pipelines/gdpr.py
bpm_tools/pipelines/io.py
bpm_tools/pipelines/partition.py
bpm_tools/pipelines/transform.py
bpm_tools-0.2.5.dist-info/LICENSE
bpm_tools-0.2.5.dist-info/METADATA
bpm_tools-0.2.5.dist-info/WHEEL
bpm_tools-0.2.5.dist-info/top_level.txt
bpm_tools-0.2.5.dist-info/RECORD
