Metadata-Version: 2.1
Name: bpm-tools
Version: 0.2.5
Summary: Shared functions for BPM data pipelines.
Home-page: UNKNOWN
Author: Cameron Tarbotton
License: UNKNOWN
Platform: UNKNOWN
Classifier: Programming Language :: Python :: 3
Classifier: License :: OSI Approved :: MIT License
Classifier: Operating System :: OS Independent
Requires-Python: >=3.6
